Workbook

Sheet Übersicht & Vergleich
B2: Vermögensaufbau & Sparplan-Vergleich (25 € bis 150 € / 5 - 15 Jahre)
B3: Übersicht über 4 Anlageoptionen inkl. Endvermögen, Renditeannahmen und Steuerbehandlung bei Auszahlung
B5: 1. Die 4 Anlagestrategien im Profil
B6: Option / Strategie | C6: Zielrendite (p.a.) | D6: Risikoprofil | E6: Kosten p.a. | F6: Steuer in Sparphase | G6: Steuer bei Einmalauszahlung | H6: Steuer bei Monatsauszahlung (Rente)
B7: Option 1: Zinssparen / Tages- & Festgeld | C7: 0.025 | D7: Sehr gering (100k Einlagensicherung) | E7: 0,00% | F7: Jährlich Abgeltungsteuer auf Zinsen (abzgl. 1.000 € Freibetrag) | G7: Bereits jährlich versteuert (keine Nachsteuer auf Kapital) | H7: Kapitalauszahlung steuerfrei, Zinsen auf Restkapital steuerpflichtig
B8: Option 2: Welt-Aktien-ETF (MSCI World / All-World) im Depot | C8: 0.07 | D8: Moderat-Höher (Kursschwankungen) | E8: ~0,20% (TER) | F8: Vorabpauschale (EZB-Basiszins x 70% abzgl. Freibetrag) | G8: Abgeltungsteuer (26,375%) auf Kursgewinne abzgl. 30% Teilfreistellung | H8: Entnahmeplan: Sukzessive Versteuerung nur des Gewinnanteils der Verkäufe (Freibetrag nutzbar)
B9: Option 3: ETF-Rentenversicherung (Fondspolice) | C9: 0.054 | D9: Moderat-Höher (ETFs im Versicherungsmantel) | E9: ~0,60% Effektivk. | F9: 100% steuerfrei (keine Vorabpauschale, steuerfreies Umschichten) | G9: Halbeinkünfteverfahren (12/62-Regel): 50% Gewinn mit persönl. Steuersatz + 15% TFS | H9: Ertragsanteilsbesteuerung (z.B. mit 67 Jahren nur 17% der Rente einkommensteuerpflichtig)
B10: Option 4: Ausgewogenes Multi-Asset Portfolio (60% ETF / 40% Zins) | C10: 0.048 | D10: Moderat-Gering (Ausgewogen) | E10: ~0,25% (TER) | F10: Zinsen jährlich, ETF via Vorabpauschale | G10: Abgeltungsteuer auf ETF-Gewinne (Mischfonds 15% TFS) & Zinsen | H10: Entnahmeplan: Steuerlich aufgeteilt nach Zins- und ETF-Gewinnanteil
B12: 2. Vermögensentwicklung: Detailvergleich aller Kombinationen
B13: Berechnung: Monatlich vorschüssige Sparrate. Werte vor Steuern (Brutto) und Schätzung des Netto-Endvermögens bei Einmalauszahlung.
B15: Monatl. Sparrate | C15: Laufzeit (Jahre) | D15: Eingezahltes Kapital | E15: Opt 1: Festgeld (2,5%) Endkapital Netto | F15: Opt 2: Welt-ETF (7,0%) Endkapital Brutto | G15: Opt 2: Welt-ETF Endkapital Netto* | H15: Opt 3: Rentenvers. (5,4%) Endkapital Netto (12/62)** | I15: Opt 4: Multi-Asset (4,8%) Endkapital Netto*
B16: 25 | C16: 5 | D16: =B16*C16*12 -> 1500 | E16: =-FV(0.025/12, C16*12, B16, 0, 1) -> 1599.3385 | F16: =-FV(0.07/12, C16*12, B16, 0, 1) -> 1800.2632 | G16: =F16-MAX(0, (F16-D16)*0.7*0.26375) -> 1744.8271 | H16: =-FV(0.054/12, C16*12, B16, 0, 1) - IF(C16>=12, (-FV(0.054/12, C16*12, B16, 0, 1)-D16)*0.85*0.5*0.3, (-FV(0.054/12, C16*12, B16, 0, 1)-D16)*0.85*0.26375) -> 1674.8274 | I16: =-FV(0.048/12, C16*12, B16, 0, 1) - MAX(0, (-FV(0.048/12, C16*12, B16, 0, 1)-D16)*0.235) -> 1651.6769
B17: 25 | C17: 10 | D17: =B17*C17*12 -> 3000 | E17: =-FV(0.025/12, C17*12, B17, 0, 1) -> 3411.3908 | F17: =-FV(0.07/12, C17*12, B17, 0, 1) -> 4352.3617 | G17: =F17-MAX(0, (F17-D17)*0.7*0.26375) -> 4102.6819 | H17: =-FV(0.054/12, C17*12, B17, 0, 1) - IF(C17>=12, (-FV(0.054/12, C17*12, B17, 0, 1)-D17)*0.85*0.5*0.3, (-FV(0.054/12, C17*12, B17, 0, 1)-D17)*0.85*0.26375) -> 3763.4947 | I17: =-FV(0.048/12, C17*12, B17, 0, 1) - MAX(0, (-FV(0.048/12, C17*12, B17, 0, 1)-D17)*0.235) -> 3654.9641
B18: 25 | C18: 15 | D18: =B18*C18*12 -> 4500 | E18: =-FV(0.025/12, C18*12, B18, 0, 1) -> 5464.4481 | F18: =-FV(0.07/12, C18*12, B18, 0, 1) -> 7970.2811 | G18: =F18-MAX(0, (F18-D18)*0.7*0.26375) -> 7329.5804 | H18: =-FV(0.054/12, C18*12, B18, 0, 1) - IF(C18>=12, (-FV(0.054/12, C18*12, B18, 0, 1)-D18)*0.85*0.5*0.3, (-FV(0.054/12, C18*12, B18, 0, 1)-D18)*0.85*0.26375) -> 6629.9875 | I18: =-FV(0.048/12, C18*12, B18, 0, 1) - MAX(0, (-FV(0.048/12, C18*12, B18, 0, 1)-D18)*0.235) -> 6105.0214
B19: 50 | C19: 5 | D19: =B19*C19*12 -> 3000 | E19: =-FV(0.025/12, C19*12, B19, 0, 1) -> 3198.677 | F19: =-FV(0.07/12, C19*12, B19, 0, 1) -> 3600.5263 | G19: =F19-MAX(0, (F19-D19)*0.7*0.26375) -> 3489.6542 | H19: =-FV(0.054/12, C19*12, B19, 0, 1) - IF(C19>=12, (-FV(0.054/12, C19*12, B19, 0, 1)-D19)*0.85*0.5*0.3, (-FV(0.054/12, C19*12, B19, 0, 1)-D19)*0.85*0.26375) -> 3349.6547 | I19: =-FV(0.048/12, C19*12, B19, 0, 1) - MAX(0, (-FV(0.048/12, C19*12, B19, 0, 1)-D19)*0.235) -> 3303.3539
B20: 50 | C20: 10 | D20: =B20*C20*12 -> 6000 | E20: =-FV(0.025/12, C20*12, B20, 0, 1) -> 6822.7816 | F20: =-FV(0.07/12, C20*12, B20, 0, 1) -> 8704.7234 | G20: =F20-MAX(0, (F20-D20)*0.7*0.26375) -> 8205.3639 | H20: =-FV(0.054/12, C20*12, B20, 0, 1) - IF(C20>=12, (-FV(0.054/12, C20*12, B20, 0, 1)-D20)*0.85*0.5*0.3, (-FV(0.054/12, C20*12, B20, 0, 1)-D20)*0.85*0.26375) -> 7526.9894 | I20: =-FV(0.048/12, C20*12, B20, 0, 1) - MAX(0, (-FV(0.048/12, C20*12, B20, 0, 1)-D20)*0.235) -> 7309.9281
B21: 50 | C21: 15 | D21: =B21*C21*12 -> 9000 | E21: =-FV(0.025/12, C21*12, B21, 0, 1) -> 10928.896 | F21: =-FV(0.07/12, C21*12, B21, 0, 1) -> 15940.562 | G21: =F21-MAX(0, (F21-D21)*0.7*0.26375) -> 14659.161 | H21: =-FV(0.054/12, C21*12, B21, 0, 1) - IF(C21>=12, (-FV(0.054/12, C21*12, B21, 0, 1)-D21)*0.85*0.5*0.3, (-FV(0.054/12, C21*12, B21, 0, 1)-D21)*0.85*0.26375) -> 13259.975 | I21: =-FV(0.048/12, C21*12, B21, 0, 1) - MAX(0, (-FV(0.048/12, C21*12, B21, 0, 1)-D21)*0.235) -> 12210.043
B22: 75 | C22: 5 | D22: =B22*C22*12 -> 4500 | E22: =-FV(0.025/12, C22*12, B22, 0, 1) -> 4798.0155 | F22: =-FV(0.07/12, C22*12, B22, 0, 1) -> 5400.7895 | G22: =F22-MAX(0, (F22-D22)*0.7*0.26375) -> 5234.4813 | H22: =-FV(0.054/12, C22*12, B22, 0, 1) - IF(C22>=12, (-FV(0.054/12, C22*12, B22, 0, 1)-D22)*0.85*0.5*0.3, (-FV(0.054/12, C22*12, B22, 0, 1)-D22)*0.85*0.26375) -> 5024.4821 | I22: =-FV(0.048/12, C22*12, B22, 0, 1) - MAX(0, (-FV(0.048/12, C22*12, B22, 0, 1)-D22)*0.235) -> 4955.0308
B23: 75 | C23: 10 | D23: =B23*C23*12 -> 9000 | E23: =-FV(0.025/12, C23*12, B23, 0, 1) -> 10234.172 | F23: =-FV(0.07/12, C23*12, B23, 0, 1) -> 13057.085 | G23: =F23-MAX(0, (F23-D23)*0.7*0.26375) -> 12308.046 | H23: =-FV(0.054/12, C23*12, B23, 0, 1) - IF(C23>=12, (-FV(0.054/12, C23*12, B23, 0, 1)-D23)*0.85*0.5*0.3, (-FV(0.054/12, C23*12, B23, 0, 1)-D23)*0.85*0.26375) -> 11290.484 | I23: =-FV(0.048/12, C23*12, B23, 0, 1) - MAX(0, (-FV(0.048/12, C23*12, B23, 0, 1)-D23)*0.235) -> 10964.892
B24: 75 | C24: 15 | D24: =B24*C24*12 -> 13500 | E24: =-FV(0.025/12, C24*12, B24, 0, 1) -> 16393.344 | F24: =-FV(0.07/12, C24*12, B24, 0, 1) -> 23910.843 | G24: =F24-MAX(0, (F24-D24)*0.7*0.26375) -> 21988.741 | H24: =-FV(0.054/12, C24*12, B24, 0, 1) - IF(C24>=12, (-FV(0.054/12, C24*12, B24, 0, 1)-D24)*0.85*0.5*0.3, (-FV(0.054/12, C24*12, B24, 0, 1)-D24)*0.85*0.26375) -> 19889.962 | I24: =-FV(0.048/12, C24*12, B24, 0, 1) - MAX(0, (-FV(0.048/12, C24*12, B24, 0, 1)-D24)*0.235) -> 18315.064
B25: 100 | C25: 5 | D25: =B25*C25*12 -> 6000 | E25: =-FV(0.025/12, C25*12, B25, 0, 1) -> 6397.354 | F25: =-FV(0.07/12, C25*12, B25, 0, 1) -> 7201.0527 | G25: =F25-MAX(0, (F25-D25)*0.7*0.26375) -> 6979.3083 | H25: =-FV(0.054/12, C25*12, B25, 0, 1) - IF(C25>=12, (-FV(0.054/12, C25*12, B25, 0, 1)-D25)*0.85*0.5*0.3, (-FV(0.054/12, C25*12, B25, 0, 1)-D25)*0.85*0.26375) -> 6699.3094 | I25: =-FV(0.048/12, C25*12, B25, 0, 1) - MAX(0, (-FV(0.048/12, C25*12, B25, 0, 1)-D25)*0.235) -> 6606.7078
B26: 100 | C26: 10 | D26: =B26*C26*12 -> 12000 | E26: =-FV(0.025/12, C26*12, B26, 0, 1) -> 13645.563 | F26: =-FV(0.07/12, C26*12, B26, 0, 1) -> 17409.447 | G26: =F26-MAX(0, (F26-D26)*0.7*0.26375) -> 16410.728 | H26: =-FV(0.054/12, C26*12, B26, 0, 1) - IF(C26>=12, (-FV(0.054/12, C26*12, B26, 0, 1)-D26)*0.85*0.5*0.3, (-FV(0.054/12, C26*12, B26, 0, 1)-D26)*0.85*0.26375) -> 15053.979 | I26: =-FV(0.048/12, C26*12, B26, 0, 1) - MAX(0, (-FV(0.048/12, C26*12, B26, 0, 1)-D26)*0.235) -> 14619.856
B27: 100 | C27: 15 | D27: =B27*C27*12 -> 18000 | E27: =-FV(0.025/12, C27*12, B27, 0, 1) -> 21857.792 | F27: =-FV(0.07/12, C27*12, B27, 0, 1) -> 31881.124 | G27: =F27-MAX(0, (F27-D27)*0.7*0.26375) -> 29318.322 | H27: =-FV(0.054/12, C27*12, B27, 0, 1) - IF(C27>=12, (-FV(0.054/12, C27*12, B27, 0, 1)-D27)*0.85*0.5*0.3, (-FV(0.054/12, C27*12, B27, 0, 1)-D27)*0.85*0.26375) -> 26519.95 | I27: =-FV(0.048/12, C27*12, B27, 0, 1) - MAX(0, (-FV(0.048/12, C27*12, B27, 0, 1)-D27)*0.235) -> 24420.086
... B30: 150 | C30: 15 | D30: =B30*C30*12 -> 27000 | E30: =-FV(0.025/12, C30*12, B30, 0, 1) -> 32786.689 | F30: =-FV(0.07/12, C30*12, B30, 0, 1) -> 47821.687 | G30: =F30-MAX(0, (F30-D30)*0.7*0.26375) -> 43977.483 | H30: =-FV(0.054/12, C30*12, B30, 0, 1) - IF(C30>=12, (-FV(0.054/12, C30*12, B30, 0, 1)-D30)*0.85*0.5*0.3, (-FV(0.054/12, C30*12, B30, 0, 1)-D30)*0.85*0.26375) -> 39779.925 | I30: =-FV(0.048/12, C30*12, B30, 0, 1) - MAX(0, (-FV(0.048/12, C30*12, B30, 0, 1)-D30)*0.235) -> 36630.128
B32: * Netto-Schätzung Einmalauszahlung: Versteuerung des gesamten Gewinns mit 26,375% Abgeltungsteuer (inkl. Soli) abzgl. gesetzl. Teilfreistellung (30% bei Aktien-ETFs).
B33: ** Rentenversicherung: Bei >= 12 Jahren Laufzeit Halbeinkünfteverfahren nach § 20 Abs. 1 Nr. 6 EStG (50% Gewinn mit indiv. Steuersatz ca. 30% versteuert abzgl. 15% TFS).
B34: Hinweis: Bei Auszahlung via monatlichem Entnahmeplan/Rente fällt die Steuerbelastung deutlich geringer bzw. zeitlich stark gestreckt an (Ausnutzung jährl. Freibetrag von 1.000 €).

Sheet Interaktiver Rechner
B2: Interaktiver Sparplan- & Auszahlungsrechner
B3: Passe die gelb hinterlegten Parameter an, um individuelle Szenarien live durchzurechnen.
B5: A. Eingabeparameter (Gelbe Felder bearbeitbar)
B7: Monatliche Sparrate (€) | D7: 100 | E7: Gewünschter monatlicher Sparbetrag (z.B. 25, 50, 75, 100, 150)
B8: Anlagedauer (Jahre) | D8: 15 | E8: Laufzeit bis zum Renten-/Auszahlungsbeginn
B9: Sparer-Pauschbetrag / Jahr (€) | D9: 1000 | E9: Gesetzlicher Steuerfreibetrag (1.000 € Single / 2.000 € Verheiratet)
B10: Abgeltungsteuersatz (+Soli) | D10: 0.26375 | E10: 25% Kapitalertragsteuer + 5,5% Soli = 26,375%
B11: Individueller Steuersatz im Alter | D11: 0.3 | E11: Geschätzter persönlicher Einkommensteuersatz im Rentenalter
B12: Entnahmedauer im Alter (Jahre) | D12: 20 | E12: Geplanter Auszahlungszeitraum für monatliche Rente
B13: Zinssatz während Entnahmephase (p.a.) | D13: 0.035 | E13: Konservative Verzinsung des verbleibenden Kapitals im Alter
B15: Renditeannahmen pro Option (p.a.)
B16: Rendite Option 1: Tages-/Festgeld | D16: 0.025
B17: Rendite Option 2: Welt-ETF (MSCI World) | D17: 0.07
B18: Rendite Option 3: Rentenversicherung (nach Fondskosten) | D18: 0.054
B19: Rendite Option 4: Multi-Asset (60/40) | D19: 0.048
B21: B. Berechnungsergebnisse bei gewählten Parametern
B22: Kennzahl / Ergebnis | C22: Option 1: Festgeld | D22: Option 2: Welt-ETF | E22: Option 3: Rentenvers. | F22: Option 4: Multi-Asset
B23: Gesamte eigene Einzahlung | C23: =$D$7*$D$8*12 -> 18000 | D23: =$D$7*$D$8*12 -> 18000 | E23: =$D$7*$D$8*12 -> 18000 | F23: =$D$7*$D$8*12 -> 18000
B24: Brutto-Endkapital vor Steuer | C24: =-FV(D16/12, $D$8*12, $D$7, 0, 1) -> 21857.792 | D24: =-FV(D17/12, $D$8*12, $D$7, 0, 1) -> 31881.124 | E24: =-FV(D18/12, $D$8*12, $D$7, 0, 1) -> 27764.986 | F24: =-FV(D19/12, $D$8*12, $D$7, 0, 1) -> 26392.269
B25: Erwirtschafteter Gesamtertrag (Gewinn) | C25: =C24-C23 -> 3857.7924 | D25: =D24-D23 -> 13881.124 | E25: =E24-E23 -> 9764.9857 | F25: =F24-F23 -> 8392.2687
B26: Steuerfreier Gewinnanteil (Teilfreistellung) | C26: =0 -> 0 | D26: =D25*0.3 -> 4164.3373 | E26: =E25*0.15 -> 1464.7478 | F26: =F25*0.15*0.6 -> 755.30419
B27: Geschätzte Steuer bei Einmalauszahlung | C27: =0 -> 0 | D27: =MAX(0, (D25-D26)*$D$10) -> 2562.8026 | E27: =IF($D$8>=12, (E25-E26)*0.5*$D$11, (E25-E26)*$D$10) -> 1245.0357 | F27: =MAX(0, (F25-F26)*$D$10) -> 2014.2494
B28: Netto-Endkapital (Einmalauszahlung) | C28: =C24-C27 -> 21857.792 | D28: =D24-D27 -> 29318.322 | E28: =E24-E27 -> 26519.95 | F28: =F24-F27 -> 24378.019
B29: Monatliche Netto-Rente (Kapitalverzehr über gewählte Jahre) | C29: =-PMT($D$13/12, $D$12*12, C28, 0, 1) -> 126.39773 | D29: =-PMT($D$13/12, $D$12*12, D28, 0, 1) -> 169.53996 | E29: =-PMT($D$13/12, $D$12*12, E28, 0, 1) -> 153.35773 | F29: =-PMT($D$13/12, $D$12*12, F28, 0, 1) -> 140.97153
B30: Ewige Rente / Monatl. Zinsertrag (ohne Kapitalverzehr) | C30: =C28*($D$13/12) -> 63.751894 | D30: =D28*($D$13/12) -> 85.511772 | E30: =E28*($D$13/12) -> 77.349854 | F30: =F28*($D$13/12) -> 71.102556

Sheet Jahresverlauf (Simulation)
B2: Jährlicher Vermögensaufbau (Jahr 1 bis 15)
B3: Entwicklung der 4 Optionen basierend auf den Eingaben im Blatt 'Interaktiver Rechner' (Sparrate: ='Interaktiver Rechner'!$D$7 €/Monat)
B5: Jahr | C5: Einzahlungen p.a. | D5: Einzahlungen Kumuliert | E5: Opt 1: Festgeld Stand Jahresende | F5: Opt 2: Welt-ETF Stand Jahresende | G5: Opt 3: Rentenvers. Stand Jahresende | H5: Opt 4: Multi-Asset Stand Jahresende
B6: 1 | C6: ='Interaktiver Rechner'!$D$7*12 -> 1200 | D6: =B6*C6 -> 1200 | E6: =-FV('Interaktiver Rechner'!$D$16/12, B6*12, 'Interaktiver Rechner'!$D$7, 0, 1) -> 1216.3748 | F6: =-FV('Interaktiver Rechner'!$D$17/12, B6*12, 'Interaktiver Rechner'!$D$7, 0, 1) -> 1246.4875 | G6: =-FV('Interaktiver Rechner'!$D$18/12, B6*12, 'Interaktiver Rechner'!$D$7, 0, 1) -> 1235.6857 | H6: =-FV('Interaktiver Rechner'!$D$19/12, B6*12, 'Interaktiver Rechner'!$D$7, 0, 1) -> 1231.6622
B7: 2 | C7: ='Interaktiver Rechner'!$D$7*12 -> 1200 | D7: =B7*C7 -> 2400 | E7: =-FV('Interaktiver Rechner'!$D$16/12, B7*12, 'Interaktiver Rechner'!$D$7, 0, 1) -> 2463.5098 | F7: =-FV('Interaktiver Rechner'!$D$17/12, B7*12, 'Interaktiver Rechner'!$D$7, 0, 1) -> 2583.0838 | G7: =-FV('Interaktiver Rechner'!$D$18/12, B7*12, 'Interaktiver Rechner'!$D$7, 0, 1) -> 2539.775 | H7: =-FV('Interaktiver Rechner'!$D$19/12, B7*12, 'Interaktiver Rechner'!$D$7, 0, 1) -> 2523.7623
B8: 3 | C8: ='Interaktiver Rechner'!$D$7*12 -> 1200 | D8: =B8*C8 -> 3600 | E8: =-FV('Interaktiver Rechner'!$D$16/12, B8*12, 'Interaktiver Rechner'!$D$7, 0, 1) -> 3742.1829 | F8: =-FV('Interaktiver Rechner'!$D$17/12, B8*12, 'Interaktiver Rechner'!$D$7, 0, 1) -> 4016.3026 | G8: =-FV('Interaktiver Rechner'!$D$18/12, B8*12, 'Interaktiver Rechner'!$D$7, 0, 1) -> 3916.0544 | H8: =-FV('Interaktiver Rechner'!$D$19/12, B8*12, 'Interaktiver Rechner'!$D$7, 0, 1) -> 3879.2661
B9: 4 | C9: ='Interaktiver Rechner'!$D$7*12 -> 1200 | D9: =B9*C9 -> 4800 | E9: =-FV('Interaktiver Rechner'!$D$16/12, B9*12, 'Interaktiver Rechner'!$D$7, 0, 1) -> 5053.1918 | F9: =-FV('Interaktiver Rechner'!$D$17/12, B9*12, 'Interaktiver Rechner'!$D$7, 0, 1) -> 5553.129 | G9: =-FV('Interaktiver Rechner'!$D$18/12, B9*12, 'Interaktiver Rechner'!$D$7, 0, 1) -> 5368.5202 | H9: =-FV('Interaktiver Rechner'!$D$19/12, B9*12, 'Interaktiver Rechner'!$D$7, 0, 1) -> 5301.2847
B10: 5 | C10: ='Interaktiver Rechner'!$D$7*12 -> 1200 | D10: =B10*C10 -> 6000 | E10: =-FV('Interaktiver Rechner'!$D$16/12, B10*12, 'Interaktiver Rechner'!$D$7, 0, 1) -> 6397.354 | F10: =-FV('Interaktiver Rechner'!$D$17/12, B10*12, 'Interaktiver Rechner'!$D$7, 0, 1) -> 7201.0527 | G10: =-FV('Interaktiver Rechner'!$D$18/12, B10*12, 'Interaktiver Rechner'!$D$7, 0, 1) -> 6901.3897 | H10: =-FV('Interaktiver Rechner'!$D$19/12, B10*12, 'Interaktiver Rechner'!$D$7, 0, 1) -> 6793.082
B11: 6 | C11: ='Interaktiver Rechner'!$D$7*12 -> 1200 | D11: =B11*C11 -> 7200 | E11: =-FV('Interaktiver Rechner'!$D$16/12, B11*12, 'Interaktiver Rechner'!$D$7, 0, 1) -> 7775.508 | F11: =-FV('Interaktiver Rechner'!$D$17/12, B11*12, 'Interaktiver Rechner'!$D$7, 0, 1) -> 8968.1049 | G11: =-FV('Interaktiver Rechner'!$D$18/12, B11*12, 'Interaktiver Rechner'!$D$7, 0, 1) -> 8519.114 | H11: =-FV('Interaktiver Rechner'!$D$19/12, B11*12, 'Interaktiver Rechner'!$D$7, 0, 1) -> 8358.0822
B12: 7 | C12: ='Interaktiver Rechner'!$D$7*12 -> 1200 | D12: =B12*C12 -> 8400 | E12: =-FV('Interaktiver Rechner'!$D$16/12, B12*12, 'Interaktiver Rechner'!$D$7, 0, 1) -> 9188.5133 | F12: =-FV('Interaktiver Rechner'!$D$17/12, B12*12, 'Interaktiver Rechner'!$D$7, 0, 1) -> 10862.897 | G12: =-FV('Interaktiver Rechner'!$D$18/12, B12*12, 'Interaktiver Rechner'!$D$7, 0, 1) -> 10226.39 | H12: =-FV('Interaktiver Rechner'!$D$19/12, B12*12, 'Interaktiver Rechner'!$D$7, 0, 1) -> 9999.8772
B13: 8 | C13: ='Interaktiver Rechner'!$D$7*12 -> 1200 | D13: =B13*C13 -> 9600 | E13: =-FV('Interaktiver Rechner'!$D$16/12, B13*12, 'Interaktiver Rechner'!$D$7, 0, 1) -> 10637.251 | F13: =-FV('Interaktiver Rechner'!$D$17/12, B13*12, 'Interaktiver Rechner'!$D$7, 0, 1) -> 12894.665 | G13: =-FV('Interaktiver Rechner'!$D$18/12, B13*12, 'Interaktiver Rechner'!$D$7, 0, 1) -> 12028.176 | H13: =-FV('Interaktiver Rechner'!$D$19/12, B13*12, 'Interaktiver Rechner'!$D$7, 0, 1) -> 11722.235
B14: 9 | C14: ='Interaktiver Rechner'!$D$7*12 -> 1200 | D14: =B14*C14 -> 10800 | E14: =-FV('Interaktiver Rechner'!$D$16/12, B14*12, 'Interaktiver Rechner'!$D$7, 0, 1) -> 12122.626 | F14: =-FV('Interaktiver Rechner'!$D$17/12, B14*12, 'Interaktiver Rechner'!$D$7, 0, 1) -> 15073.309 | G14: =-FV('Interaktiver Rechner'!$D$18/12, B14*12, 'Interaktiver Rechner'!$D$7, 0, 1) -> 13929.702 | H14: =-FV('Interaktiver Rechner'!$D$19/12, B14*12, 'Interaktiver Rechner'!$D$7, 0, 1) -> 13529.11
B15: 10 | C15: ='Interaktiver Rechner'!$D$7*12 -> 1200 | D15: =B15*C15 -> 12000 | E15: =-FV('Interaktiver Rechner'!$D$16/12, B15*12, 'Interaktiver Rechner'!$D$7, 0, 1) -> 13645.563 | F15: =-FV('Interaktiver Rechner'!$D$17/12, B15*12, 'Interaktiver Rechner'!$D$7, 0, 1) -> 17409.447 | G15: =-FV('Interaktiver Rechner'!$D$18/12, B15*12, 'Interaktiver Rechner'!$D$7, 0, 1) -> 15936.491 | H15: =-FV('Interaktiver Rechner'!$D$19/12, B15*12, 'Interaktiver Rechner'!$D$7, 0, 1) -> 15424.649
B16: 11 | C16: ='Interaktiver Rechner'!$D$7*12 -> 1200 | D16: =B16*C16 -> 13200 | E16: =-FV('Interaktiver Rechner'!$D$16/12, B16*12, 'Interaktiver Rechner'!$D$7, 0, 1) -> 15207.013 | F16: =-FV('Interaktiver Rechner'!$D$17/12, B16*12, 'Interaktiver Rechner'!$D$7, 0, 1) -> 19914.465 | G16: =-FV('Interaktiver Rechner'!$D$18/12, B16*12, 'Interaktiver Rechner'!$D$7, 0, 1) -> 18054.369 | H16: =-FV('Interaktiver Rechner'!$D$19/12, B16*12, 'Interaktiver Rechner'!$D$7, 0, 1) -> 17413.202
B17: 12 | C17: ='Interaktiver Rechner'!$D$7*12 -> 1200 | D17: =B17*C17 -> 14400 | E17: =-FV('Interaktiver Rechner'!$D$16/12, B17*12, 'Interaktiver Rechner'!$D$7, 0, 1) -> 16807.95 | F17: =-FV('Interaktiver Rechner'!$D$17/12, B17*12, 'Interaktiver Rechner'!$D$7, 0, 1) -> 22600.571 | G17: =-FV('Interaktiver Rechner'!$D$18/12, B17*12, 'Interaktiver Rechner'!$D$7, 0, 1) -> 20289.486 | H17: =-FV('Interaktiver Rechner'!$D$19/12, B17*12, 'Interaktiver Rechner'!$D$7, 0, 1) -> 19499.333
... B20: 15 | C20: ='Interaktiver Rechner'!$D$7*12 -> 1200 | D20: =B20*C20 -> 18000 | E20: =-FV('Interaktiver Rechner'!$D$16/12, B20*12, 'Interaktiver Rechner'!$D$7, 0, 1) -> 21857.792 | F20: =-FV('Interaktiver Rechner'!$D$17/12, B20*12, 'Interaktiver Rechner'!$D$7, 0, 1) -> 31881.124 | G20: =-FV('Interaktiver Rechner'!$D$18/12, B20*12, 'Interaktiver Rechner'!$D$7, 0, 1) -> 27764.986 | H20: =-FV('Interaktiver Rechner'!$D$19/12, B20*12, 'Interaktiver Rechner'!$D$7, 0, 1) -> 26392.269

Sheet Steuer-Ratgeber & Auszahlung
B2: Steuerliche Behandlung bei Ansparung & Auszahlung
B3: Rechtliche Grundlagen & Vergleich: Einmalige Kapitalauszahlung vs. Monatliche Verrentung/Entnahme
B5: 1. Gesetzliche Grundlagen für Privatanleger in Deutschland
B6: Abgeltungsteuer | C6: 25 % zzgl. 5,5 % Solidaritätszuschlag = 26,375 % (zzgl. ggf. Kirchensteuer 8-9 %). Gilt für Zinsen, Dividenden und realisierte Kursgewinne.
B7: Sparer-Pauschbetrag | C7: 1.000 € pro Person / 2.000 € bei Ehepaaren pro Jahr steuerfrei durch Freistellungsauftrag bei der Bank/Depot.
B8: Teilfreistellung (InvStG) | C8: Aktienfonds/ETFs (mind. 51% Aktien): 30 % aller Erträge und Gewinne sind steuerfrei! Bei Mischfonds (mind. 25% Aktien) sind 15 % steuerfrei.
B9: Vorabpauschale | C9: Jährliche Mindestbesteuerung thesaurierender Fonds nach Basisertrag (EZB-Zins), sofern das Depotjahr positiv verläuft. Wird bei späterem Verkauf voll angerechnet.
B11: 2. Steuervergleich bei Auszahlung (Einmalbetrag vs. Monatliche Rente)
B12: Direkt-Depot ETF (Option 2) | C12: EINMALAUSZAHLUNG: Gesamter Gewinn wird im Verkaufsjahr versteuert (abzgl. 30% TFS & 1.000 € Freibetrag). MONATLICHER ENTZUG: Bei monatlichen Teilverkäufen wird nur der Gewinnanteil der verkauften Tranche versteuert. Durch die Aufteilung über 15-20 Jahre kann jedes Jahr der Sparerpauschbetrag voll genutzt werden -> Extrem steuergünstig!
B13: Rentenversicherung (Option 3)
B14: Festgeld / Zinssparen (Option 1) | C14: EINMALAUSZAHLUNG / ENTZUG: Zinsen wurden bereits jährlich im Zuflussjahr versteuert. Bei Auszahlung fällt keinerlei Nachsteuer auf das Kapital an.
B15: Multi-Asset Portfolio (Option 4) | C15: EINMALAUSZAHLUNG: Zinsbausteine jährlich versteuert, ETF-Gewinne beim Verkauf mit 15% TFS versteuert. MONATLICHER ENTZUG: Entnahme zuerst aus dem Zins-/Cash-Topf, gezielter Verkauf von ETF-Anteilen zur Freibetragsoptimierung.
B17: 3. Zusammenfassung & Handlungsempfehlung je nach Zeithorizont
B18: 5 Jahre (Kurzfristig) | C18: Fokus auf Sicherheit und Werterhalt. Empfehlung: Option 1 (Tages-/Festgeld) oder Option 4 mit hohem Zinsanteil. Aktienquote sollte wegen möglicher Kursrücksetzer gering gehalten werden.
B19: 10 Jahre (Mittelfristig) | C19: Option 2 (Welt-ETF) oder Option 4 (Multi-Asset). Bei 10 Jahren Laufzeit überwiegen die Renditechancen von Aktien deutlich, Risiko durch zeitliche Streuung beherrschbar.
B20: 15+ Jahre (Langfristig / Rente) | C20: Option 2 (Welt-ETF im Direkt-Depot) für maximale Rendite und Flexibilität ODER Option 3 (Fondsgebundene Rentenversicherung) für maximale Steuerbegünstigung im Alter und lebenslange Rentengarantie.
